colomoto_docker.py
colomoto_docker-9.3.dist-info/METADATA
colomoto_docker-9.3.dist-info/WHEEL
colomoto_docker-9.3.dist-info/entry_points.txt
colomoto_docker-9.3.dist-info/top_level.txt
colomoto_docker-9.3.dist-info/RECORD
