Metadata-Version: 2.4
Name: colomoto-docker
Version: 9.3
Summary: Helper script to run docker image colomoto/colomoto-docker
Home-page: https://github.com/colomoto/colomoto-docker-py
Author: Loïc Paulevé
Author-email: loic.pauleve@ens-cachan.org
Requires-Dist: donodo
Dynamic: author
Dynamic: author-email
Dynamic: home-page
Dynamic: requires-dist
Dynamic: summary
